[
    {
        "name": "24-10 Studio Prime Gramercy WD in Unit",
        "url": "https://www.booking.com/hotel/us/24-10-studio-prime-gramercy-wd-in-unit.en-gb.html",
        "aggregateRating": {
            "ratingValue": 9.0,
            "bestRating": 10,
            "reviewCount": 1,
            "@type": "AggregateRating"
        },
        "image": "https://cf.bstatic.com/xdata/images/hotel/max500/531819492.jpg?k=855e079acceb184a0192764c3804726f7f0b3c4ef21fe1437592f9ab0fa59520&o=&hp=1",
        "hasMap": "https://maps.googleapis.com/maps/api/staticmap?center=40.7389107,-73.9808273&size=1600x1200&zoom=15&sensor=false&markers=color:blue%7c40.7389107,-73.9808273&client=gme-booking&channel=booking-frontend&signature=HcZuikjODfFAtl-8MMRFP0FkCa0=",
        "@type": "Hotel",
        "address": {
            "addressRegion": "New York State",
            "postalCode": "10010",
            "streetAddress": "241 East 24th Street, Gramercy, New York, 10010, United States",
            "addressLocality": "241 East 24th Street",
            "addressCountry": "USA",
            "@type": "PostalAddress"
        },
        "@context": "http://schema.org",
        "description": "Set in New York, less than 1 km from Flatiron Building and a 18-minute walk from Empire State Building, 24-10 Studio Prime Gramercy WD in Unit offers air...",
        "priceRange": "Prices for upcoming dates start at \u00a3330 per night (We Price Match)"
    }
]